screenmonkey/__init__.py
screenmonkey/screenmonkey.py
screenmonkey-0.1.0.dist-info/LICENSE
screenmonkey-0.1.0.dist-info/METADATA
screenmonkey-0.1.0.dist-info/WHEEL
screenmonkey-0.1.0.dist-info/top_level.txt
screenmonkey-0.1.0.dist-info/RECORD
