Metadata-Version: 2.1
Name: screenmonkey
Version: 0.1.0
Summary: Packing for recording and executing on-screen actions
Home-page: https://github.com/bmerrill17/screenmonkey
Author: brycemerrill
Author-email: brycelmerrill@gmail.com
License: UNKNOWN
Platform: UNKNOWN
Classifier: Programming Language :: Python :: 3
Classifier: License :: OSI Approved :: MIT License
Classifier: Operating System :: OS Independent
Requires-Python: >=3.6
License-File: LICENSE
Requires-Dist: pandas
Requires-Dist: openpyxl
Requires-Dist: pynput
